flask_weixin.py
Flask_Weixin-0.5.0.dist-info/DESCRIPTION.rst
Flask_Weixin-0.5.0.dist-info/METADATA
Flask_Weixin-0.5.0.dist-info/metadata.json
Flask_Weixin-0.5.0.dist-info/pbr.json
Flask_Weixin-0.5.0.dist-info/RECORD
Flask_Weixin-0.5.0.dist-info/top_level.txt
Flask_Weixin-0.5.0.dist-info/WHEEL
