Metadata-Version: 2.0
Name: Flask-Weixin
Version: 0.5.0
Summary: Weixin for Flask.
Home-page: https://github.com/lepture/flask-weixin
Author: Hsiaoming Yang
Author-email: me@lepture.com
License: BSD
Platform: any
Classifier: Development Status :: 4 - Beta
Classifier: Environment :: Web Environment
Classifier: Intended Audience :: Developers
Classifier: License :: OSI Approved :: BSD License
Classifier: Operating System :: OS Independent
Classifier: Programming Language :: Python
Classifier: Topic :: Internet :: WWW/HTTP :: Dynamic Content
Classifier: Topic :: Software Development :: Libraries :: Python Modules
